{"cameraMode":{"drawMode":0,"name":"Shaded","section":"Shading Mode"},"sceneLighting":true,"audioPlay":false,"sceneViewState":{"m_AlwaysRefresh":false,"showFog":true,"showSkybox":true,"showFlares":true,"showImageEffects":true,"showParticleSystems":true,"showVisualEffectGraphs":true,"m_FxEnabled":true},"in2DMode":false,"pivot":{"x":-198.42233276367188,"y":19.616567611694337,"z":2808.69091796875},"rotation":{"x":-0.13114233314990998,"y":-0.7058770060539246,"z":0.13081276416778565,"w":-0.6867232322692871},"size":9.582290649414063,"orthographic":false}